inferelator/__init__.py
inferelator/crossvalidation_workflow.py
inferelator/workflow.py
inferelator/benchmarking/__init__.py
inferelator/benchmarking/celloracle.py
inferelator/benchmarking/scenic.py
inferelator/distributed/__init__.py
inferelator/distributed/dask.py
inferelator/distributed/dask_cluster_controller.py
inferelator/distributed/dask_k8_controller.py
inferelator/distributed/dask_local_controller.py
inferelator/distributed/inferelator_mp.py
inferelator/distributed/joblib_controller.py
inferelator/distributed/local_controller.py
inferelator/postprocessing/__init__.py
inferelator/postprocessing/_plot_fix.py
inferelator/postprocessing/column_names.py
inferelator/postprocessing/f1_score.py
inferelator/postprocessing/inferelator_results.py
inferelator/postprocessing/matthews_correlation.py
inferelator/postprocessing/model_metrics.py
inferelator/postprocessing/model_performance.py
inferelator/postprocessing/precision_recall.py
inferelator/postprocessing/results_processor.py
inferelator/postprocessing/results_processor_mtl.py
inferelator/predict/__init__.py
inferelator/predict/dynamic.py
inferelator/predict/static.py
inferelator/preprocessing/__init__.py
inferelator/preprocessing/data_normalization.py
inferelator/preprocessing/design_response_translation.py
inferelator/preprocessing/metadata_parser.py
inferelator/preprocessing/priors.py
inferelator/preprocessing/simulate_data.py
inferelator/preprocessing/single_cell.py
inferelator/preprocessing/tfa.py
inferelator/preprocessing/velocity.py
inferelator/regression/__init__.py
inferelator/regression/amusr_math.py
inferelator/regression/amusr_regression.py
inferelator/regression/base_regression.py
inferelator/regression/bayes_stats.py
inferelator/regression/bbsr_multitask.py
inferelator/regression/bbsr_python.py
inferelator/regression/elasticnet_python.py
inferelator/regression/mi.py
inferelator/regression/sklearn_regression.py
inferelator/regression/stability_selection.py
inferelator/tfa/__init__.py
inferelator-0.6.3.dist-info/LICENSE
inferelator-0.6.3.dist-info/METADATA
inferelator-0.6.3.dist-info/WHEEL
inferelator-0.6.3.dist-info/top_level.txt
inferelator-0.6.3.dist-info/RECORD
