Metadata-Version: 2.1
Name: inferelator
Version: 0.6.3
Summary: Inferelator: Network Inference
Home-page: https://github.com/flatironinstitute/inferelator
Author: Chris Jackson
Author-email: cj59@nyu.edu
Maintainer: Chris Jackson
Maintainer-email: cj59@nyu.edu
Project-URL: Documentation, https://inferelator.readthedocs.io/
Classifier: Programming Language :: Python :: 3
Classifier: License :: OSI Approved :: BSD License
Classifier: Operating System :: OS Independent
Classifier: Development Status :: 4 - Beta
Requires-Python: >=3.8
License-File: LICENSE
Requires-Dist: numpy >=1.14.0
Requires-Dist: scipy >=0.9
Requires-Dist: pandas >=0.24.0
Requires-Dist: scikit-learn
Requires-Dist: matplotlib >=1.5.1
Requires-Dist: anndata >=0.9.0
